mitosheet/__init__.py
mitosheet/__main__.py
mitosheet/_frontend.py
mitosheet/_version.py
mitosheet/column_headers.py
mitosheet/data_in_mito.py
mitosheet/errors.py
mitosheet/mito_widget.py
mitosheet/parser.py
mitosheet/state.py
mitosheet/step.py
mitosheet/steps_manager.py
mitosheet/types.py
mitosheet/utils.py
mitosheet/api/__init__.py
mitosheet/api/api.py
mitosheet/api/get_column_describe.py
mitosheet/api/get_column_summary_graph.py
mitosheet/api/get_csv_files_metadata.py
mitosheet/api/get_dataframe_as_csv.py
mitosheet/api/get_dataframe_as_excel.py
mitosheet/api/get_excel_file_metadata.py
mitosheet/api/get_params.py
mitosheet/api/get_path_contents.py
mitosheet/api/get_path_join.py
mitosheet/api/get_split_text_to_columns_preview.py
mitosheet/api/get_unique_value_counts.py
mitosheet/code_chunks/__init__.py
mitosheet/code_chunks/add_column_set_formula_code_chunk.py
mitosheet/code_chunks/code_chunk.py
mitosheet/code_chunks/code_chunk_utils.py
mitosheet/code_chunks/delete_row_code_chunk.py
mitosheet/code_chunks/empty_code_chunk.py
mitosheet/code_chunks/melt_code_chunk.py
mitosheet/code_chunks/no_op_code_chunk.py
mitosheet/code_chunks/one_hot_encoding_code_chunk.py
mitosheet/code_chunks/promote_row_to_header_code_chunk.py
mitosheet/code_chunks/transpose_code_chunk.py
mitosheet/code_chunks/postprocessing/__init__.py
mitosheet/code_chunks/postprocessing/set_dataframe_format_code_chunk.py
mitosheet/code_chunks/step_performers/__init__.py
mitosheet/code_chunks/step_performers/concat_code_chunk.py
mitosheet/code_chunks/step_performers/drop_duplicates_code_chunk.py
mitosheet/code_chunks/step_performers/fill_na_code_chunk.py
mitosheet/code_chunks/step_performers/filter_code_chunk.py
mitosheet/code_chunks/step_performers/merge_code_chunk.py
mitosheet/code_chunks/step_performers/pivot_code_chunk.py
mitosheet/code_chunks/step_performers/set_cell_value_code_chunk.py
mitosheet/code_chunks/step_performers/sort_code_chunk.py
mitosheet2-0.1.61.dist-info/LICENSE.txt
mitosheet2-0.1.61.dist-info/METADATA
mitosheet2-0.1.61.dist-info/WHEEL
mitosheet2-0.1.61.dist-info/top_level.txt
mitosheet2-0.1.61.dist-info/RECORD
