Metadata-Version: 2.1
Name: mitosheet2
Version: 0.1.61
Summary: The Mito Spreadsheet
Home-page: https://github.com/mito-ds/monorepo
Author: Mito
Author-email: naterush1997@gmail.com
License: GNU Affero General Public License v3
Keywords: Jupyter,Widgets,IPython
Platform: Linux
Platform: Mac OS X
Platform: Windows
Classifier: Intended Audience :: Developers
Classifier: Intended Audience :: Science/Research
Classifier: License :: OSI Approved :: GNU Affero General Public License v3
Classifier: Programming Language :: Python
Classifier: Programming Language :: Python :: 3
Classifier: Programming Language :: Python :: 3.6
Classifier: Programming Language :: Python :: 3.7
Classifier: Programming Language :: Python :: 3.8
Classifier: Programming Language :: Python :: 3.9
Classifier: Framework :: Jupyter
Requires-Dist: jupyterlab (!=2.3.0,!=2.3.1,<3.0,>=2.0)
Requires-Dist: ipywidgets (~=7.0.0)
Requires-Dist: pandas (>=0.24.2)
Requires-Dist: analytics-python
Requires-Dist: plotly (>=4.14.3)
Requires-Dist: chardet (>=3.0.4)
Requires-Dist: openpyxl
Requires-Dist: xlsxwriter (<=3.0.2,>=0.6.9)
Provides-Extra: deploy
Requires-Dist: wheel ; extra == 'deploy'
Requires-Dist: twine ; extra == 'deploy'
Requires-Dist: jupyter-packaging (<=0.10.6) ; extra == 'deploy'
Requires-Dist: setuptools (==56.0.0) ; extra == 'deploy'
Provides-Extra: test
Requires-Dist: pytest ; extra == 'test'
Requires-Dist: flake8 ; extra == 'test'
Requires-Dist: types-chardet ; extra == 'test'
Requires-Dist: mypy ; extra == 'test'
